{
    "paths": [
        {
            "name": "/apply",
            "lambdaFunction": "startapplication",
            "privacy": {
                "private": true,
                "auth": [
                    "/POST"
                ]
            }
        }
    ],
    "resourceName": "startapplication",
    "apiName": "startapplication",
    "functionArns": [
        {
            "lambdaFunction": "startapplication"
        }
    ],
    "privacy": {
        "auth": 1,
        "unauth": 0,
        "authRoleName": "ukripoc-application-develop-20190524142452-authRole",
        "unAuthRoleName": "ukripoc-application-develop-20190524142452-unauthRole"
    },
    "dependsOn": [
        {
            "category": "function",
            "resourceName": "startapplication",
            "attributes": [
                "Name",
                "Arn"
            ]
        }
    ]
}